<!--
    - Policies are applied in the order they appear.
    - Position <base/> inside a section to inherit policies from the outer scope.
    - Comments within policies are not preserved.
-->
<!-- Add policies as children to the <inbound>, <outbound>, <backend>, and <on-error> elements -->
<policies>
	<!-- Throttle, authorize, validate, cache, or transform the requests -->
	<inbound>
		<base />
		<!-- <set-backend-service base-url="https://mtls.tif.feiaz.ferguson.com" /> -->
		<set-backend-service backend-id="mtls-tif-feiaz-ferguson-com" />
		<rewrite-uri template="/hello" copy-unmatched-params="true" />
		<!-- <authentication-certificate thumbprint="9D057182A9009CDAE697727F40E2632FC0DDF44B" /> -->
	</inbound>
	<!-- Control if and how the requests are forwarded to services  -->
	<backend>
		<!-- <set-backend-service backend-id="mtls-tif-feiaz-ferguson-com" /> -->
		<base />
	</backend>
	<!-- Customize the responses -->
	<outbound>
		<base />
	</outbound>
	<!-- Handle exceptions and customize error responses  -->
	<on-error>
		<base />
	</on-error>
</policies>